LICENSE
MANIFEST.in
README.rst
VERSION
requirements.txt
setup.cfg
setup.py
unicore/__init__.py
unicore/__init__.pyc
unicore.webhooks.egg-info/PKG-INFO
unicore.webhooks.egg-info/SOURCES.txt
unicore.webhooks.egg-info/dependency_links.txt
unicore.webhooks.egg-info/entry_points.txt
unicore.webhooks.egg-info/namespace_packages.txt
unicore.webhooks.egg-info/not-zip-safe
unicore.webhooks.egg-info/requires.txt
unicore.webhooks.egg-info/top_level.txt
unicore/webhooks/__init__.py
unicore/webhooks/__init__.pyc
unicore/webhooks/conftest.py
unicore/webhooks/conftest.pyc
unicore/webhooks/events.py
unicore/webhooks/events.pyc
unicore/webhooks/models.py
unicore/webhooks/models.pyc
unicore/webhooks/views.py
unicore/webhooks/views.pyc
unicore/webhooks/alembic/README
unicore/webhooks/alembic/env.py
unicore/webhooks/alembic/script.py.mako
unicore/webhooks/alembic/versions/3d506c9d6c2_.py
unicore/webhooks/tests/__init__.py
unicore/webhooks/tests/__init__.pyc
unicore/webhooks/tests/test_views.py
unicore/webhooks/tests/__pycache__/test_views.cpython-27-PYTEST.pyc