Metadata-Version: 1.1
Name: unicore.webhooks
Version: 0.0.3
Summary: Webhook tools for Universal Core
Home-page: http://github.com/universalcore/unicore.webhooks
Author: Praekelt Foundation
Author-email: dev@praekelt.com
License: BSD
Keywords: universal,core
Platform: UNKNOWN
Classifier: Programming Language :: Python
Classifier: Framework :: Pyramid
Classifier: Topic :: Internet :: WWW/HTTP
Classifier: Topic :: Internet :: WWW/HTTP :: WSGI :: Application
